simplecli/__init__.py
simplecli/simplecli.py
pysimplecli-1.0.6.dist-info/METADATA
pysimplecli-1.0.6.dist-info/WHEEL
pysimplecli-1.0.6.dist-info/RECORD
