Metadata-Version: 2.1
Name: pysimplecli
Version: 1.0.6
Summary: Easily turn functions into command line utilities
Author: Clif Bratcher
Author-email: cebratcher@gmail.com
Requires-Python: >=3.9,<4.0
Classifier: Programming Language :: Python :: 3
Classifier: Programming Language :: Python :: 3.9
Classifier: Programming Language :: Python :: 3.10
Classifier: Programming Language :: Python :: 3.11
Classifier: Programming Language :: Python :: 3.12
